keycloak_oauth/__init__.py
keycloak_oauth/ckan_user.py
keycloak_oauth/controller.py
keycloak_oauth/plugin.py
keycloak_oauth/routing.py
ckanext_keycloak_oauth-0.1.3.dist-info/METADATA
ckanext_keycloak_oauth-0.1.3.dist-info/WHEEL
ckanext_keycloak_oauth-0.1.3.dist-info/entry_points.txt
ckanext_keycloak_oauth-0.1.3.dist-info/top_level.txt
ckanext_keycloak_oauth-0.1.3.dist-info/RECORD
