Metadata-Version: 2.4
Name: ckanext-keycloak-oauth
Version: 0.1.3
Summary: CKAN extension for Keycloak OAuth2 authentication
Home-page: https://github.com/theinhnam/ckanext-keycloak-oauth
Author: Nam Nguyen Duy Thanh
Author-email: namndt1773@gmail.com
License: MIT
Classifier: Programming Language :: Python :: 3
Classifier: License :: OSI Approved :: MIT License
Classifier: Operating System :: OS Independent
Requires-Python: >=3.6
Requires-Dist: requests-oauthlib
Requires-Dist: beaker
Dynamic: author
Dynamic: author-email
Dynamic: classifier
Dynamic: description-content-type
Dynamic: home-page
Dynamic: license
Dynamic: requires-dist
Dynamic: requires-python
Dynamic: summary
